pomodoro/__init__.py
pomodoro/__main__.py
pomodoro/assets/alarm-default.mp3
pomodoro/assets/icon.png
pomodoro_Dev3XoR-0.8.5.dist-info/LICENSE
pomodoro_Dev3XoR-0.8.5.dist-info/METADATA
pomodoro_Dev3XoR-0.8.5.dist-info/WHEEL
pomodoro_Dev3XoR-0.8.5.dist-info/entry_points.txt
pomodoro_Dev3XoR-0.8.5.dist-info/top_level.txt
pomodoro_Dev3XoR-0.8.5.dist-info/zip-safe
pomodoro_Dev3XoR-0.8.5.dist-info/RECORD
