Metadata-Version: 2.1
Name: pomodoro-Dev3XoR
Version: 0.8.5
Summary: Pomodoro clock and timer
Home-page: https://github.com/Dev3XOR/pomodoro/
Author: Dev3XoR
Author-email: devexor@protonmail.com
License: UNKNOWN
Platform: UNKNOWN
Classifier: Programming Language :: Python :: 3
Classifier: License :: OSI Approved :: MIT License
Classifier: Operating System :: OS Independent
Requires-Python: ~=3.6
License-File: LICENSE
Requires-Dist: playsound
Requires-Dist: plyer
